<?xml version="1.0" encoding="UTF-8"?>
<feature
      id="de.cooperateproject.rcptt.ecl.cdoserver.feature"
      label="ECL Commands for CDO Server Controlling"
      version="1.0.0.qualifier">

   <description url="http://www.example.com/description">
      Adds ECL commands to start and stop a in-memory CDO server.
   </description>

   <copyright url="http://www.example.com/copyright">
      [Enter Copyright Description here.]
   </copyright>

   <license url="http://www.example.com/license">
      [Enter License Description here.]
   </license>

   <requires>
      <import plugin="org.eclipse.core.runtime"/>
      <import plugin="org.eclipse.emf.ecore"/>
      <import plugin="org.eclipse.rcptt.ecl.core"/>
      <import plugin="org.eclipse.emf.cdo" version="4.5.0" match="greaterOrEqual"/>
      <import plugin="org.eclipse.emf.cdo.net4j" version="4.1.400" match="greaterOrEqual"/>
      <import plugin="org.eclipse.emf.cdo.server" version="4.5.0" match="greaterOrEqual"/>
      <import plugin="org.eclipse.emf.cdo.server.db" version="4.4.0" match="greaterOrEqual"/>
      <import plugin="org.eclipse.emf.cdo.server.net4j" version="4.1.300" match="greaterOrEqual"/>
      <import plugin="org.eclipse.net4j" version="4.5.0" match="greaterOrEqual"/>
      <import plugin="org.eclipse.net4j.jvm" version="4.1.400" match="greaterOrEqual"/>
      <import plugin="org.eclipse.net4j.db.h2" version="4.2.300" match="greaterOrEqual"/>
      <import plugin="org.h2" version="1.3.168" match="greaterOrEqual"/>
   </requires>

   <plugin
         id="de.cooperateproject.rcptt.ecl.cdoserver"
         download-size="0"
         install-size="0"
         version="0.0.0"
         unpack="false"/>

</feature>
